{
  "specs": {
    "lifecycle": {
      "versions": {
        "v1.0": {
          "schema": "schema/lifecycle/v1.0.schema.json",
          "zod": "./schema/lifecycle.ts",
          "export": "LifecycleSpec",
          "docs": "spec/lifecycle/v1.0-tables.md",
          "status": "stable"
        }
      },
      "latest": "v1.0"
    },
    "process": {
      "versions": {
        "v1.0": {
          "schema": "schema/process/v1.0.schema.json",
          "zod": "./schema/process.ts",
          "export": "ProcessSpec",
          "docs": "spec/process/v1.0-tables.md",
          "status": "stable"
        }
      },
      "latest": "v1.0"
    }
  }
}